ai_helper_lib/__init__.py
ai_helper_lib/core.py
ai_helper_lib-0.1.0.dist-info/METADATA
ai_helper_lib-0.1.0.dist-info/WHEEL
ai_helper_lib-0.1.0.dist-info/top_level.txt
ai_helper_lib-0.1.0.dist-info/RECORD
