Metadata-Version: 2.4
Name: ai_helper_lib
Version: 0.1.0
Summary: A helper library for interacting with Anti Gravity AI
Author: Student Name
Author-email: student@example.com
Classifier: Programming Language :: Python :: 3
Classifier: License :: OSI Approved :: MIT License
Classifier: Operating System :: OS Independent
Requires-Python: >=3.6
Requires-Dist: google-generativeai
Dynamic: author
Dynamic: author-email
Dynamic: classifier
Dynamic: description
Dynamic: description-content-type
Dynamic: requires-dist
Dynamic: requires-python
Dynamic: summary
